any_cast/__init__.py
any_cast/binary_sequences.py
any_cast/booleans.py
any_cast/errors.py
any_cast/mappings.py
any_cast/numerics.py
any_cast/objects.py
any_cast/sequences.py
any_cast/sets.py
any_cast/text_sequences.py
any_cast-0.0.3.dist-info/METADATA
any_cast-0.0.3.dist-info/WHEEL
any_cast-0.0.3.dist-info/licenses/LICENSE
any_cast-0.0.3.dist-info/RECORD
