Metadata-Version: 2.1
Name: any_cast
Version: 0.0.3
Summary: Attempt to cast any value to a specified type
Project-URL: Homepage, https://github.com/Braden2n/AnyCast
Project-URL: Documentation, https://github.com/Braden2n/AnyCast
Project-URL: Issues, https://github.com/Braden2n/AnyCast/issues
Project-URL: Repository, https://github.com
Project-URL: Changelog, https://github.com/Braden2n/AnyCast/activity
Author-email: Braden Toone <braden@toonetown.com>
Maintainer-email: Braden Toone <braden@toonetown.com>
License: MIT License
License-File: LICENSE
Keywords: cast,casting,type,types
Classifier: Development Status :: 2 - Pre-Alpha
Classifier: Intended Audience :: Developers
Classifier: License :: OSI Approved :: MIT License
Classifier: Natural Language :: English
Classifier: Operating System :: OS Independent
Classifier: Programming Language :: Python :: 3.3
Classifier: Topic :: Software Development :: Libraries :: Python Modules
Requires-Python: >=3.3
